PanMCL/__init__.py
PanMCL/cli.py
PanMCL/core_test_2.py
PanMCL/core_test_3.py
PanMCL/gff_cds_pep_deal.py
PanMCL/orthogroups_identity.py
PanMCL/orthogroups_identity_V3.py
PanMCL/run_blast_diamond.py
PanMCL/run_interproscan_2.py
PanMCL/run_mcscanx_V4.py
PanMCL-0.7.7.dist-info/METADATA
PanMCL-0.7.7.dist-info/WHEEL
PanMCL-0.7.7.dist-info/entry_points.txt
PanMCL-0.7.7.dist-info/top_level.txt
PanMCL-0.7.7.dist-info/RECORD
